drjax/__init__.py
drjax/_src/__init__.py
drjax/_src/api.py
drjax/_src/impls.py
drjax/_src/primitives.py
drjax-0.1.4.dist-info/licenses/LICENSE
drjax-0.1.4.dist-info/METADATA
drjax-0.1.4.dist-info/WHEEL
drjax-0.1.4.dist-info/top_level.txt
drjax-0.1.4.dist-info/RECORD
