Metadata-Version: 2.4
Name: drjax
Version: 0.1.4
Summary: DrJAX - Scalable and Differentiable MapReduce Primitives in JAX.
Author-email: Keith Rush <krush@google.com>, Zachary Charles <zachcharles@google.com>, Zachary Garrett <zachgarrett@google.com>
License: 
Project-URL: Homepage, https://github.com/google/drjax
Project-URL: Repository, https://github.com/google/drjax
Keywords: parallel,mapreduce,machine,learning,jax
Classifier: License :: OSI Approved :: Apache Software License
Classifier: Intended Audience :: Science/Research
Requires-Python: >=3.9
License-File: LICENSE
Requires-Dist: absl-py<3.0,>=1.0
Requires-Dist: jax>=0.4.24
Requires-Dist: jaxlib>=0.4.24
Dynamic: license-file
